phenio_toolkit/__init__.py
phenio_toolkit/cli.py
phenio_toolkit/cross_species/__init__.py
phenio_toolkit/mapping/lexical_mapping.py
phenio_toolkit/notebooks/lexical_mapping.ipynb
phenio_toolkit/phenio_cli.py
phenio_toolkit-0.1.5.dist-info/LICENSE
phenio_toolkit-0.1.5.dist-info/METADATA
phenio_toolkit-0.1.5.dist-info/WHEEL
phenio_toolkit-0.1.5.dist-info/entry_points.txt
phenio_toolkit-0.1.5.dist-info/RECORD
