Metadata-Version: 2.1
Name: phenio-toolkit
Version: 0.1.5
Summary: phenio-toolkit
License: MIT
Author: Vinicius de Souza
Author-email: souzadevinicius@gmail.com
Requires-Python: >=3.9,<4.0
Classifier: License :: OSI Approved :: MIT License
Classifier: Programming Language :: Python :: 3
Classifier: Programming Language :: Python :: 3.9
Classifier: Programming Language :: Python :: 3.10
Classifier: Programming Language :: Python :: 3.11
Classifier: Programming Language :: Python :: 3.12
Provides-Extra: docs
Requires-Dist: click (>=8.1.3)
Requires-Dist: curies (>=0.7.4,<0.8.0)
Requires-Dist: importlib-metadata (>=6.8.0,<7.0.0)
Requires-Dist: oaklib (>=0.5.6,<0.6.0)
Requires-Dist: pandas (>=2.0.1,<3.0.0)
